README.md
setup.cfg
setup.py
igrf12/__init__.py
igrf12/base.py
igrf12/plots.py
igrf12/utils.py
igrf12.egg-info/PKG-INFO
igrf12.egg-info/SOURCES.txt
igrf12.egg-info/dependency_links.txt
igrf12.egg-info/requires.txt
igrf12.egg-info/top_level.txt
src/igrf11.f
src/igrf12.f