Metadata-Version: 2.1
Name: igrf12
Version: 1.3.6
Summary: IGRF12 model with simple object-oriented Python interface.
Home-page: https://github.com/space-physics/igrf12
Author: Michael Hirsch, Ph.D.
Author-email: scivision@users.noreply.github.com
License: UNKNOWN
Keywords: geomagnetic,igrf
Platform: UNKNOWN
Classifier: Development Status :: 5 - Production/Stable
Classifier: Environment :: Console
Classifier: Intended Audience :: Science/Research
Classifier: Operating System :: OS Independent
Classifier: Programming Language :: Fortran
Classifier: Programming Language :: Python :: 3.6
Classifier: Programming Language :: Python :: 3.7
Classifier: Programming Language :: Python :: 3.8
Classifier: Topic :: Scientific/Engineering :: Atmospheric Science
Requires-Python: >=3.6
Provides-Extra: tests
Provides-Extra: lint
Provides-Extra: plot
